pybeepop/__init__.py
pybeepop/analysis.py
pybeepop/clean_data.py
pybeepop/eda.py
pybeepop/to_ddl.py
pybeepop-0.1.3.dist-info/LICENSE
pybeepop-0.1.3.dist-info/METADATA
pybeepop-0.1.3.dist-info/WHEEL
pybeepop-0.1.3.dist-info/RECORD
