Metadata-Version: 2.1
Name: pybeepop
Version: 0.1.3
Summary: Assessing the Influence of Pesticide Usage, Parasitic Factors, and Climate on Honey Bee Populations in the United States (2015-2019)
License: MIT
Author: Hanlin Zhao
Requires-Python: >=3.11.9,<4.0.0
Classifier: License :: OSI Approved :: MIT License
Classifier: Programming Language :: Python :: 3
Classifier: Programming Language :: Python :: 3.12
Requires-Dist: altair (==5.2.0)
Requires-Dist: matplotlib (==3.8.3)
Requires-Dist: mysql-connector-python (==8.3)
Requires-Dist: pandas (==2.2.2)
Requires-Dist: scikit-learn (==1.2.0)
Requires-Dist: seaborn (==0.13.2)
Requires-Dist: shap (==0.45.0)
Requires-Dist: statsmodels (==0.14.1)
Requires-Dist: us (==3.1.1)
Requires-Dist: vegafusion (==1.6.5)
Requires-Dist: vl-convert-python (==1.2.3)
Requires-Dist: xgboost (==2.0.3)
